manim_course_utils/__init__.py
manim_course_utils/animation_description.py
manim_course_utils/mobject_description.py
manim_course_utils/rst_mobject.py
manim_course_utils-1.0.1.dist-info/METADATA
manim_course_utils-1.0.1.dist-info/WHEEL
manim_course_utils-1.0.1.dist-info/RECORD
