Metadata-Version: 2.1
Name: manim-course-utils
Version: 1.0.1
Summary: Para el curso de ManimCE de MathLike
Home-page: https://github.com/MathLike/manim-course-utils
Author: MathLike
Author-email: benjamin.ubilla@uc.cl
Requires-Python: >=3.8,<3.13
Classifier: Programming Language :: Python :: 3
Classifier: Programming Language :: Python :: 3.8
Classifier: Programming Language :: Python :: 3.9
Classifier: Programming Language :: Python :: 3.10
Classifier: Programming Language :: Python :: 3.11
Classifier: Programming Language :: Python :: 3.12
Requires-Dist: manim (>=0.18.0)
Requires-Dist: setuptools (>=68.2.2)
Project-URL: Repository, https://github.com/MathLike/manim-course-utils
